hfinder/__init__.py
hfinder/__main__.py
hfinder-1.0.2.dist-info/LICENSE
hfinder-1.0.2.dist-info/METADATA
hfinder-1.0.2.dist-info/WHEEL
hfinder-1.0.2.dist-info/entry_points.txt
hfinder-1.0.2.dist-info/top_level.txt
hfinder-1.0.2.dist-info/RECORD
