Metadata-Version: 2.1
Name: hfinder
Version: 1.0.2
Summary: hfinder
Home-page: https://github.com/cosad3s/hfinder
Author: Sébastien Copin
Author-email: cosad3s@outlook.com
License: GPL-3.0 License
Keywords: hostnames,cidr,asn,network,discovery,osint,bugbounty
Classifier: Topic :: Internet :: WWW/HTTP :: Indexing/Search
Classifier: Topic :: Security
Classifier: Programming Language :: Python :: 3
License-File: LICENSE
Requires-Dist: beautifulsoup4
Requires-Dist: requests
Requires-Dist: argparse
Requires-Dist: webdriver-manager
Requires-Dist: selenium
